django_loki_reloaded/__init__.py
django_loki_reloaded/formatters.py
django_loki_reloaded/handlers.py
django_loki_reloaded-1.0.3.dist-info/LICENSE
django_loki_reloaded-1.0.3.dist-info/METADATA
django_loki_reloaded-1.0.3.dist-info/WHEEL
django_loki_reloaded-1.0.3.dist-info/top_level.txt
django_loki_reloaded-1.0.3.dist-info/RECORD
